<?xml version = '1.0' encoding = 'UTF-8'?>
<FKIndexAssociation class="oracle.dbtools.crest.model.design.relational.FKIndexAssociation" directorySegmentName="seg_0" id="3116952A-145C-832F-A1A7-FDD3F99C529D" containerWithKeyObject="DC638E54-A7FE-95E7-589B-D07222760ED2" localFKIndex="DA7EC671-3D69-5F5A-EAE9-9B589C9B80FF" name="FK_LINEORDER_EMPLOYEEID">
<sourceConnName>CoffeHouse</sourceConnName>
<sourceObjSchema>SYS</sourceObjSchema>
<sourceObjName>FK_LINEORDER_EMPLOYEEID</sourceObjName>
<createdBy>HP</createdBy>
<createdTime>2023-09-11 20:33:57 UTC</createdTime>
<ownerDesignName>12</ownerDesignName>
<referredTableLongName>SYS.EMPLOYEE</referredTableLongName>
<deleteRule>NO ACTION</deleteRule>
<referredTableID>2251B06D-DB47-95FC-A8A7-E9A4CD2CE2E7</referredTableID>
<keyObject>8A3A8A1A-6423-A8AC-685D-FBBDB568A4B9</keyObject>
<referredKeyID>8A3A8A1A-6423-A8AC-685D-FBBDB568A4B9</referredKeyID>
<mandatory>true</mandatory>
<refColNames>EMPLOYEEID</refColNames>
<transferable>true</transferable>
<rely>false</rely>
<columnDependencyConstraintGenerateInDDL>true</columnDependencyConstraintGenerateInDDL>
</FKIndexAssociation>